README.md
setup.py
pulumi_proxmox/__init__.py
pulumi_proxmox/_inputs.py
pulumi_proxmox/_tables.py
pulumi_proxmox/_utilities.py
pulumi_proxmox/cluster_alias.py
pulumi_proxmox/get_cluster_alias.py
pulumi_proxmox/get_cluster_aliases.py
pulumi_proxmox/get_nodes.py
pulumi_proxmox/get_version.py
pulumi_proxmox/outputs.py
pulumi_proxmox/provider.py
pulumi_proxmox/py.typed
pulumi_proxmox.egg-info/PKG-INFO
pulumi_proxmox.egg-info/SOURCES.txt
pulumi_proxmox.egg-info/dependency_links.txt
pulumi_proxmox.egg-info/not-zip-safe
pulumi_proxmox.egg-info/requires.txt
pulumi_proxmox.egg-info/top_level.txt
pulumi_proxmox/config/__init__.py
pulumi_proxmox/config/outputs.py
pulumi_proxmox/config/vars.py
pulumi_proxmox/ct/__init__.py
pulumi_proxmox/ct/_inputs.py
pulumi_proxmox/ct/container.py
pulumi_proxmox/ct/outputs.py
pulumi_proxmox/permission/__init__.py
pulumi_proxmox/permission/_inputs.py
pulumi_proxmox/permission/get_group.py
pulumi_proxmox/permission/get_groups.py
pulumi_proxmox/permission/get_pool.py
pulumi_proxmox/permission/get_pools.py
pulumi_proxmox/permission/get_role.py
pulumi_proxmox/permission/get_roles.py
pulumi_proxmox/permission/get_user.py
pulumi_proxmox/permission/get_users.py
pulumi_proxmox/permission/group.py
pulumi_proxmox/permission/outputs.py
pulumi_proxmox/permission/pool.py
pulumi_proxmox/permission/role.py
pulumi_proxmox/permission/user.py
pulumi_proxmox/storage/__init__.py
pulumi_proxmox/storage/_inputs.py
pulumi_proxmox/storage/file.py
pulumi_proxmox/storage/get_datastores.py
pulumi_proxmox/storage/outputs.py
pulumi_proxmox/system/__init__.py
pulumi_proxmox/system/_inputs.py
pulumi_proxmox/system/certifi.py
pulumi_proxmox/system/dns.py
pulumi_proxmox/system/get_dns.py
pulumi_proxmox/system/get_hosts.py
pulumi_proxmox/system/get_time.py
pulumi_proxmox/system/hosts.py
pulumi_proxmox/system/outputs.py
pulumi_proxmox/system/time.py
pulumi_proxmox/vm/__init__.py
pulumi_proxmox/vm/_inputs.py
pulumi_proxmox/vm/outputs.py
pulumi_proxmox/vm/virtual_machine.py