Metadata-Version: 2.1
Name: pulumi-proxmox
Version: 0.0.6
Summary: A Pulumi Provider which adds support for Proxmox solutions.
Home-page: https://github.com/ryan4yin/pulumi-proxmox
License: Apache-2.0
Project-URL: Repository, https://github.com/ryan4yin/pulumi-proxmox
Keywords: pulumi proxmox
Platform: UNKNOWN
